odoo/addons/auth_ldaps/README.rst
odoo/addons/auth_ldaps/__init__.py
odoo/addons/auth_ldaps/__manifest__.py
odoo/addons/auth_ldaps/i18n/auth_ldaps.pot
odoo/addons/auth_ldaps/i18n/it.po
odoo/addons/auth_ldaps/models/__init__.py
odoo/addons/auth_ldaps/models/res_company_ldap.py
odoo/addons/auth_ldaps/readme/CONFIGURE.md
odoo/addons/auth_ldaps/readme/CONTRIBUTORS.md
odoo/addons/auth_ldaps/readme/CREDITS.md
odoo/addons/auth_ldaps/readme/DESCRIPTION.md
odoo/addons/auth_ldaps/readme/INSTALL.md
odoo/addons/auth_ldaps/readme/USAGE.md
odoo/addons/auth_ldaps/static/description/icon.png
odoo/addons/auth_ldaps/static/description/index.html
odoo/addons/auth_ldaps/views/res_company_ldap_views.xml
odoo_addon_auth_ldaps-17.0.1.0.0.4.dist-info/METADATA
odoo_addon_auth_ldaps-17.0.1.0.0.4.dist-info/WHEEL
odoo_addon_auth_ldaps-17.0.1.0.0.4.dist-info/top_level.txt
odoo_addon_auth_ldaps-17.0.1.0.0.4.dist-info/RECORD
