Metadata-Version: 2.1
Name: odoo-addon-auth_ldaps
Version: 17.0.1.0.0.4
Requires-Python: >=3.10
Requires-Dist: odoo>=17.0a,<17.1dev
Requires-Dist: python-ldap
Summary: Allows to use LDAP over SSL authentication
Home-page: https://github.com/OCA/server-auth
License: AGPL-3
Author: CorporateHub, Creu Blanca, Odoo Community Association (OCA)
Author-email: support@odoo-community.org
Classifier: Programming Language :: Python
Classifier: Framework :: Odoo
Classifier: Framework :: Odoo :: 17.0
Classifier: License :: OSI Approved :: GNU Affero General Public License v3
